imgscrapy/__init__.py
imgscrapy/exceptions.py
imgscrapy/main.py
imgscrapy/utils.py
imgscrapy-1.0.0.dist-info/LICENSE.txt
imgscrapy-1.0.0.dist-info/METADATA
imgscrapy-1.0.0.dist-info/WHEEL
imgscrapy-1.0.0.dist-info/entry_points.txt
imgscrapy-1.0.0.dist-info/top_level.txt
imgscrapy-1.0.0.dist-info/RECORD
