Metadata-Version: 2.1
Name: imgscrapy
Version: 1.0.0
Summary: A simple CLI image scraper tool with support for headless scraping of dynamic websites.
Home-page: https://github.com/arutselvan/ImgScrapy
Author: Arut Selvan
Author-email: arutselvan710@gmail.com
License: MIT
Platform: UNKNOWN
Classifier: Programming Language :: Python :: 3
Classifier: License :: OSI Approved :: MIT License
Classifier: Operating System :: OS Independent
Requires-Python: >=3.6
Requires-Dist: requests (==2.23.0)
Requires-Dist: lxml (==4.5.0)
Requires-Dist: clint (==0.5.1)
Requires-Dist: pyfiglet (==0.8.post1)
Requires-Dist: progressbar33 (==2.4)
Requires-Dist: pyppeteer (==0.2.2)
